schemamacros/__init__.py
schemamacros/cli.py
schemamacros/compile.py
schemamacros/config.py
schemamacros-0.2.2.dist-info/DESCRIPTION.rst
schemamacros-0.2.2.dist-info/METADATA
schemamacros-0.2.2.dist-info/RECORD
schemamacros-0.2.2.dist-info/WHEEL
schemamacros-0.2.2.dist-info/entry_points.txt
schemamacros-0.2.2.dist-info/metadata.json
schemamacros-0.2.2.dist-info/top_level.txt
tests/__init__.py
tests/conftest.py
tests/test_cli.py
tests/test_compile.py
tests/test_config.py
tests/schema/__init__.py
