Metadata-Version: 2.0
Name: schemamacros
Version: 0.2.2
Summary: Template SQL
Home-page: https://github.com/caj-larsson/schemamacros
Author: Caj Larsson
Author-email: contact@caj.me
License: MIT
Platform: any
Classifier: Environment :: Web Environment
Classifier: Intended Audience :: Developers
Classifier: License :: OSI Approved :: MIT License
Classifier: Operating System :: OS Independent
Classifier: Programming Language :: Python
Classifier: Topic :: Internet :: WWW/HTTP :: Dynamic Content
Classifier: Topic :: Software Development :: Libraries :: Python Modules
Requires-Dist: Click
Requires-Dist: attrs
Requires-Dist: jinja2
Requires-Dist: pyaml
